metahb/__init__.py
metahb/app/__init__.py
metahb/app/detection.py
metahb/app/segment.py
metahb/model_zoo/__init__.py
metahb/model_zoo/model.py
metahb/utils/__init__.py
metahb/utils/general.py
meta_hb-0.1.0.dist-info/METADATA
meta_hb-0.1.0.dist-info/WHEEL
meta_hb-0.1.0.dist-info/top_level.txt
meta_hb-0.1.0.dist-info/zip-safe
meta_hb-0.1.0.dist-info/RECORD
