Metadata-Version: 2.1
Name: meta-hb
Version: 0.1.0
Summary: Meta HB Toolkit
Home-page: https://github.com/CachCheng/metahb
Author: CachCheng
Author-email: tkggpdc2007@163.com
License: Apache-2.0
Platform: UNKNOWN
Requires-Dist: opencv-python
Requires-Dist: setuptools
Requires-Dist: numpy
Requires-Dist: meta-cv
